{
  "admin": [
    {
      "username": "winkwinkwinkz",
      "password": 1151,
      "id": 1
    }
  ],
  "articles": [
    {
      "title": "saaaa",
      "tag": "1",
      "date": {
        "createdAt": 1678364419144,
        "lastUpdated": 1678364554922
      },
      "description": "aaa",
      "paragraph": [
        {
          "content": "aaa",
          "id": 1
        }
      ],
      "id": 1
    },
    {
      "title": "ccc",
      "tag": "2",
      "date": {
        "createdAt": 1578364433278,
        "lastUpdated": null
      },
      "description": "ddd",
      "paragraph": [
        {
          "content": "ddd",
          "id": 1
        }
      ],
      "id": 2
    },
    {
      "title": "blllllllll",
      "tag": "3",
      "date": {
        "createdAt": 1478364574491,
        "lastUpdated": null
      },
      "description": "a",
      "paragraph": [
        {
          "content": "a",
          "id": 1
        }
      ],
      "id": 3
    },
    {
      "title": "dlahsdjbasljdb",
      "tag": "a",
      "date": {
        "createdAt": 1678368339863,
        "lastUpdated": 1678368392002
      },
      "description": "",
      "paragraph": [
        {
          "content": "",
          "id": 1
        }
      ],
      "id": 4
    },
    {
      "title": "liahsdjas;kdjas",
      "tag": "a",
      "date": {
        "createdAt": 1678368348136,
        "lastUpdated": 1678368419800
      },
      "description": "",
      "paragraph": [
        {
          "content": "",
          "id": 1
        }
      ],
      "id": 5
    },
    {
      "title": "pppajsdkas",
      "tag": "a",
      "date": {
        "createdAt": 1678368359435,
        "lastUpdated": 1678368404904
      },
      "description": "",
      "paragraph": [
        {
          "content": "",
          "id": 1
        }
      ],
      "id": 6
    },
    {
      "title": "111111111",
      "tag": "a",
      "date": {
        "createdAt": 1678368366894,
        "lastUpdated": 1678368411959
      },
      "description": "",
      "paragraph": [
        {
          "content": "",
          "id": 1
        }
      ],
      "id": 7
    }
  ]
}